niebla/__init__.py
niebla/dust_absorption_models.py
niebla/dust_reemission_models.py
niebla/ebl_model.py
niebla/measurements.py
niebla/metall_models.py
niebla/safe_log10.py
niebla/sfr_models.py
niebla/data/logo_small.png
niebla/data/Swire_library/Ell13_template_norm.sed
niebla/data/measurements/emissivities_finke22.txt
niebla/data/measurements/ebl_intensity/all_freq/CB_complete.txt
niebla/data/measurements/ebl_intensity/optical_data_2023/CIB/altieri1999.ecsv
niebla/data/measurements/ebl_intensity/optical_data_2023/CIB/bethermin2012.ecsv
niebla/data/measurements/ebl_intensity/optical_data_2023/CIB/clements1999.ecsv
niebla/data/measurements/ebl_intensity/optical_data_2023/CIB/driver2016.ecsv
niebla/data/measurements/ebl_intensity/optical_data_2023/CIB/finkbeiner2000.ecsv
niebla/data/measurements/ebl_intensity/optical_data_2023/CIB/fujimoto2016.ecsv
niebla/data/measurements/ebl_intensity/optical_data_2023/CIB/hopwood2010.ecsv
niebla/data/measurements/ebl_intensity/optical_data_2023/CIB/hsu2016.ecsv
niebla/data/measurements/ebl_intensity/optical_data_2023/CIB/juvela2009.ecsv
niebla/data/measurements/ebl_intensity/optical_data_2023/CIB/marsden2009.ecsv
niebla/data/measurements/ebl_intensity/optical_data_2023/CIB/matsuura2011.ecsv
niebla/data/measurements/ebl_intensity/optical_data_2023/CIB/odegard2007.ecsv
niebla/data/measurements/ebl_intensity/optical_data_2023/CIB/odegard2019.ecsv
niebla/data/measurements/ebl_intensity/optical_data_2023/CIB/penin2012.ecsv
niebla/data/measurements/ebl_intensity/optical_data_2023/COB/aapostmann2024.ecsv
niebla/data/measurements/ebl_intensity/optical_data_2023/COB/biteau2015.ecsv
niebla/data/measurements/ebl_intensity/optical_data_2023/COB/biteau2015_gamma_only.ecsv
niebla/data/measurements/ebl_intensity/optical_data_2023/COB/brown2000.ecsv
niebla/data/measurements/ebl_intensity/optical_data_2023/COB/chiang2019.ecsv
niebla/data/measurements/ebl_intensity/optical_data_2023/COB/edelstein2000.ecsv
niebla-0.0.18.dist-info/licenses/LICENSE
niebla-0.0.18.dist-info/METADATA
niebla-0.0.18.dist-info/WHEEL
niebla-0.0.18.dist-info/top_level.txt
niebla-0.0.18.dist-info/RECORD
