Metadata-Version: 2.4
Name: niebla
Version: 0.0.18
Summary: Python package to compute the EBL with a forward folding approach.
Home-page: https://github.com/saraporrasbedmar/niebla
Author: Sara Porras Bedmar
Author-email: Sara Porras Bedmar <saraporrasbedmar@gmail.com>
License-Expression: BSD-3-Clause
Project-URL: Homepage, https://github.com/saraporrasbedmar/niebla
Project-URL: Issues, https://github.com/saraporrasbedmar/niebla/issues
Keywords: 'extragalactic background light','EBL','gamma-ray','opacity'
Classifier: Programming Language :: Python :: 3
Classifier: Operating System :: OS Independent
Requires-Python: >=3.7, <4
License-File: LICENSE
Requires-Dist: numpy>=1.19
Requires-Dist: scipy>=1.5
Requires-Dist: astropy>=4.0
Requires-Dist: matplotlib
Dynamic: author
Dynamic: home-page
Dynamic: keywords
Dynamic: license-file
Dynamic: requires-dist
Dynamic: requires-python
